dreamstack/__init__.py
dreamstack/__main__.py
dreamstack/__version__.py
dreamstack/core.py
dreamstack-0.0.1.dist-info/METADATA
dreamstack-0.0.1.dist-info/WHEEL
dreamstack-0.0.1.dist-info/entry_points.txt
dreamstack-0.0.1.dist-info/licenses/LICENSE
dreamstack-0.0.1.dist-info/RECORD
