Metadata-Version: 2.4
Name: dreamstack
Version: 0.0.1
Summary: A Python library for demonstration and publishing to PyPI.
License-File: LICENSE
Keywords: scape,dreamstack
Author: Scape Agency
Author-email: info@scape.agency
Maintainer: Lars van Vianen
Maintainer-email: lars@scape.agency
Requires-Python: >=3.12,<4.0
Classifier: Development Status :: 5 - Production/Stable
Classifier: Intended Audience :: Developers
Classifier: License :: Other/Proprietary License
Classifier: Natural Language :: English
Classifier: Operating System :: OS Independent
Classifier: Environment :: Web Environment
Classifier: Framework :: Django
Classifier: Programming Language :: Python :: 3
Classifier: Programming Language :: Python :: 3 :: Only
Classifier: Programming Language :: Python :: 3.12
Classifier: Programming Language :: Python :: 3.13
Classifier: Programming Language :: Python :: 3.14
Classifier: Topic :: Software Development :: Libraries :: Python Modules
Classifier: Topic :: Software Development :: Libraries :: Application Frameworks
Classifier: Topic :: Internet :: WWW/HTTP
Classifier: Topic :: Internet :: WWW/HTTP :: Dynamic Content
Classifier: Topic :: Internet :: WWW/HTTP :: WSGI
Requires-Dist: rite (>=0.0.13,<0.0.14)
Project-URL: Documentation, https://github.com/scape-agency/dreamstack/doc
Project-URL: Homepage, https://scape.agency/
Project-URL: Repository, https://github.com/scape-agency/dreamstack
